neo_grammar_graph/__init__.py
neo_grammar_graph/gg.py
neo_grammar_graph/helpers.py
neo_grammar_graph/nodes.py
neo_grammar_graph/type_defs.py
neo_grammar_graph-0.2.3.dist-info/LICENSE
neo_grammar_graph-0.2.3.dist-info/METADATA
neo_grammar_graph-0.2.3.dist-info/WHEEL
neo_grammar_graph-0.2.3.dist-info/top_level.txt
neo_grammar_graph-0.2.3.dist-info/RECORD
