Metadata-Version: 2.1
Name: neo-grammar-graph
Version: 0.2.3
Summary: Graphs from Context-Free Grammars.
Home-page: https://github.com/rindPHI/NeoGrammarGraph
Author: Dominic Steinhöfel
Author-email: Dominic Steinhöfel <dominic.steinhoefel@cispa.de>
License: GNU GENERAL PUBLIC LICENSE
Project-URL: Homepage, https://github.com/rindPHI/NeoGrammarGraph/
Project-URL: Bug Tracker, https://github.com/rindPHI/NeoGrammarGraph/issues
Classifier: Intended Audience :: Science/Research
Classifier: License :: OSI Approved :: GNU General Public License v3 (GPLv3)
Classifier: Programming Language :: Python :: 3
Classifier: Operating System :: OS Independent
Classifier: Topic :: Scientific/Engineering
Requires-Python: >=3.10
License-File: LICENSE
Requires-Dist: bidict >=0.22.1
Requires-Dist: numpy >=1.24.2
Requires-Dist: proxyorderedset >=0.3.3
Requires-Dist: scipy >=1.10.1
Provides-Extra: dev
Requires-Dist: black >=22.8.0 ; extra == 'dev'
Requires-Dist: build >=0.8.0 ; extra == 'dev'
Requires-Dist: flake8 >=5.0.4 ; extra == 'dev'
Requires-Dist: twine >=4.0.1 ; extra == 'dev'
Provides-Extra: test
Requires-Dist: pytest-pycharm >=0.7.0 ; extra == 'test'
Requires-Dist: pytest-xdist ==2.5.0 ; extra == 'test'
Requires-Dist: pytest >=6.2.5 ; extra == 'test'
Requires-Dist: pytest-cov >=3.0.0 ; extra == 'test'
Requires-Dist: pytest-html >=3.1.1 ; extra == 'test'
Requires-Dist: pytest-randomly >=3.12.0 ; extra == 'test'
